[
  {
    "cr": 0,
    "xp": 10,
    "prof": 2,
    "ac": 13,
    "hp": "1-6",
    "hpsep": 2,
    "hpmin": 1,
    "hpmax": 6,
    "atk": 3,
    "dmg": "0-1",
    "dmgsep": 2,
    "dmgmin": 0,
    "dmgmax": 1,
    "savedc": 13
  },
  {
    "cr": 0.125,
    "xp": 25,
    "prof": 2,
    "ac": 13,
    "hp": "7-35",
    "hpsep": 2,
    "hpmin": 7,
    "hpmax": 35,
    "atk": 3,
    "dmg": "2-3",
    "dmgsep": 2,
    "dmgmin": 2,
    "dmgmax": 3,
    "savedc": 13
  },
  {
    "cr": 0.25,
    "xp": 50,
    "prof": 2,
    "ac": 13,
    "hp": "36-49",
    "hpsep": 3,
    "hpmin": 36,
    "hpmax": 49,
    "atk": 3,
    "dmg": "4-5",
    "dmgsep": 2,
    "dmgmin": 4,
    "dmgmax": 5,
    "savedc": 13
  },
  {
    "cr": 0.5,
    "xp": 100,
    "prof": 2,
    "ac": 13,
    "hp": "50-70",
    "hpsep": 3,
    "hpmin": 50,
    "hpmax": 70,
    "atk": 3,
    "dmg": "6-8",
    "dmgsep": 2,
    "dmgmin": 6,
    "dmgmax": 8,
    "savedc": 13
  },
  {
    "cr": 1,
    "xp": 200,
    "prof": 2,
    "ac": 13,
    "hp": "71-85",
    "hpsep": 3,
    "hpmin": 71,
    "hpmax": 85,
    "atk": 3,
    "dmg": "9-14",
    "dmgsep": 2,
    "dmgmin": 9,
    "dmgmax": 14,
    "savedc": 13
  },
  {
    "cr": 2,
    "xp": 450,
    "prof": 2,
    "ac": 13,
    "hp": "86-100",
    "hpsep": 3,
    "hpmin": 86,
    "hpmax": 100,
    "atk": 3,
    "dmg": "15-20",
    "dmgsep": 3,
    "dmgmin": 15,
    "dmgmax": 20,
    "savedc": 13
  },
  {
    "cr": 3,
    "xp": 700,
    "prof": 2,
    "ac": 13,
    "hp": "101-115",
    "hpsep": 4,
    "hpmin": 101,
    "hpmax": 115,
    "atk": 4,
    "dmg": "21-26",
    "dmgsep": 3,
    "dmgmin": 21,
    "dmgmax": 26,
    "savedc": 13
  },
  {
    "cr": 4,
    "xp": 1100,
    "prof": 2,
    "ac": 14,
    "hp": "116-130",
    "hpsep": 4,
    "hpmin": 116,
    "hpmax": 130,
    "atk": 5,
    "dmg": "27-32",
    "dmgsep": 3,
    "dmgmin": 27,
    "dmgmax": 32,
    "savedc": 14
  },
  {
    "cr": 5,
    "xp": 1800,
    "prof": 3,
    "ac": 15,
    "hp": "131-145",
    "hpsep": 4,
    "hpmin": 131,
    "hpmax": 145,
    "atk": 6,
    "dmg": "33-38",
    "dmgsep": 3,
    "dmgmin": 33,
    "dmgmax": 38,
    "savedc": 15
  },
  {
    "cr": 6,
    "xp": 2300,
    "prof": 3,
    "ac": 15,
    "hp": "146-160",
    "hpsep": 4,
    "hpmin": 146,
    "hpmax": 160,
    "atk": 6,
    "dmg": "39-44",
    "dmgsep": 3,
    "dmgmin": 39,
    "dmgmax": 44,
    "savedc": 15
  },
  {
    "cr": 7,
    "xp": 2900,
    "prof": 3,
    "ac": 15,
    "hp": "161-175",
    "hpsep": 4,
    "hpmin": 161,
    "hpmax": 175,
    "atk": 6,
    "dmg": "45-50",
    "dmgsep": 3,
    "dmgmin": 45,
    "dmgmax": 50,
    "savedc": 15
  },
  {
    "cr": 8,
    "xp": 3900,
    "prof": 3,
    "ac": 16,
    "hp": "176-190",
    "hpsep": 4,
    "hpmin": 176,
    "hpmax": 190,
    "atk": 7,
    "dmg": "51-56",
    "dmgsep": 3,
    "dmgmin": 51,
    "dmgmax": 56,
    "savedc": 16
  },
  {
    "cr": 9,
    "xp": 5000,
    "prof": 4,
    "ac": 16,
    "hp": "191-205",
    "hpsep": 4,
    "hpmin": 191,
    "hpmax": 205,
    "atk": 7,
    "dmg": "57-62",
    "dmgsep": 3,
    "dmgmin": 57,
    "dmgmax": 62,
    "savedc": 16
  },
  {
    "cr": 10,
    "xp": 5900,
    "prof": 4,
    "ac": 17,
    "hp": "206-220",
    "hpsep": 4,
    "hpmin": 206,
    "hpmax": 220,
    "atk": 7,
    "dmg": "63-68",
    "dmgsep": 3,
    "dmgmin": 63,
    "dmgmax": 68,
    "savedc": 16
  },
  {
    "cr": 11,
    "xp": 7200,
    "prof": 4,
    "ac": 17,
    "hp": "221-235",
    "hpsep": 4,
    "hpmin": 221,
    "hpmax": 235,
    "atk": 8,
    "dmg": "69-74",
    "dmgsep": 3,
    "dmgmin": 69,
    "dmgmax": 74,
    "savedc": 17
  },
  {
    "cr": 12,
    "xp": 8400,
    "prof": 4,
    "ac": 17,
    "hp": "236-250",
    "hpsep": 4,
    "hpmin": 236,
    "hpmax": 250,
    "atk": 8,
    "dmg": "75-80",
    "dmgsep": 3,
    "dmgmin": 75,
    "dmgmax": 80,
    "savedc": 18
  },
  {
    "cr": 13,
    "xp": 10000,
    "prof": 5,
    "ac": 18,
    "hp": "251-265",
    "hpsep": 4,
    "hpmin": 251,
    "hpmax": 265,
    "atk": 8,
    "dmg": "81-86",
    "dmgsep": 3,
    "dmgmin": 81,
    "dmgmax": 86,
    "savedc": 18
  },
  {
    "cr": 14,
    "xp": 11500,
    "prof": 5,
    "ac": 18,
    "hp": "266-280",
    "hpsep": 4,
    "hpmin": 266,
    "hpmax": 280,
    "atk": 8,
    "dmg": "87-92",
    "dmgsep": 3,
    "dmgmin": 87,
    "dmgmax": 92,
    "savedc": 18
  },
  {
    "cr": 15,
    "xp": 13000,
    "prof": 5,
    "ac": 18,
    "hp": "281-295",
    "hpsep": 4,
    "hpmin": 281,
    "hpmax": 295,
    "atk": 8,
    "dmg": "93-98",
    "dmgsep": 3,
    "dmgmin": 93,
    "dmgmax": 98,
    "savedc": 18
  },
  {
    "cr": 16,
    "xp": 15000,
    "prof": 5,
    "ac": 18,
    "hp": "296-310",
    "hpsep": 4,
    "hpmin": 296,
    "hpmax": 310,
    "atk": 9,
    "dmg": "99-104",
    "dmgsep": 3,
    "dmgmin": 99,
    "dmgmax": 104,
    "savedc": 18
  },
  {
    "cr": 17,
    "xp": 18000,
    "prof": 6,
    "ac": 19,
    "hp": "311-325",
    "hpsep": 4,
    "hpmin": 311,
    "hpmax": 325,
    "atk": 10,
    "dmg": "105-110",
    "dmgsep": 4,
    "dmgmin": 105,
    "dmgmax": 110,
    "savedc": 19
  },
  {
    "cr": 18,
    "xp": 20000,
    "prof": 6,
    "ac": 19,
    "hp": "326-340",
    "hpsep": 4,
    "hpmin": 326,
    "hpmax": 340,
    "atk": 10,
    "dmg": "111-116",
    "dmgsep": 4,
    "dmgmin": 111,
    "dmgmax": 116,
    "savedc": 19
  },
  {
    "cr": 19,
    "xp": 22000,
    "prof": 6,
    "ac": 19,
    "hp": "341-355",
    "hpsep": 4,
    "hpmin": 341,
    "hpmax": 355,
    "atk": 10,
    "dmg": "117-122",
    "dmgsep": 4,
    "dmgmin": 117,
    "dmgmax": 122,
    "savedc": 19
  },
  {
    "cr": 20,
    "xp": 25000,
    "prof": 6,
    "ac": 19,
    "hp": "356-400",
    "hpsep": 4,
    "hpmin": 356,
    "hpmax": 400,
    "atk": 10,
    "dmg": "123-140",
    "dmgsep": 4,
    "dmgmin": 123,
    "dmgmax": 140,
    "savedc": 19
  },
  {
    "cr": 21,
    "xp": 33000,
    "prof": 7,
    "ac": 19,
    "hp": "401-445",
    "hpsep": 4,
    "hpmin": 401,
    "hpmax": 445,
    "atk": 11,
    "dmg": "141-158",
    "dmgsep": 4,
    "dmgmin": 141,
    "dmgmax": 158,
    "savedc": 20
  },
  {
    "cr": 22,
    "xp": 41000,
    "prof": 7,
    "ac": 19,
    "hp": "446-490",
    "hpsep": 4,
    "hpmin": 446,
    "hpmax": 490,
    "atk": 11,
    "dmg": "159-176",
    "dmgsep": 4,
    "dmgmin": 159,
    "dmgmax": 176,
    "savedc": 20
  },
  {
    "cr": 23,
    "xp": 50000,
    "prof": 7,
    "ac": 19,
    "hp": "491-535",
    "hpsep": 4,
    "hpmin": 491,
    "hpmax": 535,
    "atk": 11,
    "dmg": "177-194",
    "dmgsep": 4,
    "dmgmin": 177,
    "dmgmax": 194,
    "savedc": 20
  },
  {
    "cr": 24,
    "xp": 62000,
    "prof": 7,
    "ac": 19,
    "hp": "536-580",
    "hpsep": 4,
    "hpmin": 536,
    "hpmax": 580,
    "atk": 11,
    "dmg": "195-212",
    "dmgsep": 4,
    "dmgmin": 195,
    "dmgmax": 212,
    "savedc": 21
  },
  {
    "cr": 25,
    "xp": 75000,
    "prof": 8,
    "ac": 19,
    "hp": "581-625",
    "hpsep": 4,
    "hpmin": 581,
    "hpmax": 625,
    "atk": 12,
    "dmg": "213-230",
    "dmgsep": 4,
    "dmgmin": 213,
    "dmgmax": 230,
    "savedc": 21
  },
  {
    "cr": 26,
    "xp": 90000,
    "prof": 8,
    "ac": 19,
    "hp": "626-670",
    "hpsep": 4,
    "hpmin": 626,
    "hpmax": 670,
    "atk": 12,
    "dmg": "231-248",
    "dmgsep": 4,
    "dmgmin": 231,
    "dmgmax": 248,
    "savedc": 21
  },
  {
    "cr": 27,
    "xp": 105000,
    "prof": 8,
    "ac": 19,
    "hp": "671-715",
    "hpsep": 4,
    "hpmin": 671,
    "hpmax": 715,
    "atk": 13,
    "dmg": "249-266",
    "dmgsep": 4,
    "dmgmin": 249,
    "dmgmax": 266,
    "savedc": 22
  },
  {
    "cr": 28,
    "xp": 120000,
    "prof": 8,
    "ac": 19,
    "hp": "716-760",
    "hpsep": 4,
    "hpmin": 716,
    "hpmax": 760,
    "atk": 13,
    "dmg": "267-284",
    "dmgsep": 4,
    "dmgmin": 267,
    "dmgmax": 284,
    "savedc": 22
  },
  {
    "cr": 29,
    "xp": 135000,
    "prof": 9,
    "ac": 19,
    "hp": "760-805",
    "hpsep": 4,
    "hpmin": 760,
    "hpmax": 805,
    "atk": 13,
    "dmg": "285-302",
    "dmgsep": 4,
    "dmgmin": 285,
    "dmgmax": 302,
    "savedc": 22
  },
  {
    "cr": 30,
    "xp": 155000,
    "prof": 9,
    "ac": 19,
    "hp": "805-850",
    "hpsep": 4,
    "hpmin": 805,
    "hpmax": 850,
    "atk": 14,
    "dmg": "303-320",
    "dmgsep": 4,
    "dmgmin": 303,
    "dmgmax": 320,
    "savedc": 23
  }
]
